{"_type":"export","__export_format":4,"__export_date":"2019-09-10T17:45:01.432Z","__export_source":"insomnia.desktop.app:v6.6.2","resources":[{"_id":"req_d0aecd2eb7684048ad30968d460355c2","authentication":{"token":"{{ token  }}","type":"bearer"},"body":{},"created":1568131957012,"description":"","headers":[],"isPrivate":false,"metaSortKey":-1568131957012,"method":"GET","modified":1568131991937,"name":"List","parameters":[],"parentId":"fld_7ac5c035c486492ab3eecaaf62c51657","settingDisableRenderRequestBody":false,"settingEncodeUrl":true,"settingRebuildPath":true,"settingSendCookies":true,"settingStoreCookies":true,"url":"{{ base_url  }}/organizing","_type":"request"},{"_id":"fld_7ac5c035c486492ab3eecaaf62c51657","created":1568131944604,"description":"","environment":{},"environmentPropertyOrder":null,"metaSortKey":-1568131944604,"modified":1568131944604,"name":"Organizing","parentId":"wrk_531746874d7b40d9a80c930c58d287b1","_type":"request_group"},{"_id":"wrk_531746874d7b40d9a80c930c58d287b1","created":1566858214680,"description":"","modified":1568132876120,"name":"Meetapp","parentId":null,"_type":"workspace"},{"_id":"req_141e0496e1814466845ab6a283af59a5","authentication":{"token":"{{ token  }}","type":"bearer"},"body":{},"created":1568132072597,"description":"","headers":[],"isPrivate":false,"metaSortKey":-1568132072597,"method":"GET","modified":1568132106848,"name":"List","parameters":[],"parentId":"fld_6103a24d36194f93ac5815061b1c8830","settingDisableRenderRequestBody":false,"settingEncodeUrl":true,"settingRebuildPath":true,"settingSendCookies":true,"settingStoreCookies":true,"url":"{{ base_url  }}/subscriptions","_type":"request"},{"_id":"fld_6103a24d36194f93ac5815061b1c8830","created":1568129864210,"description":"","environment":{},"environmentPropertyOrder":null,"metaSortKey":-1568129864210,"modified":1568129864210,"name":"Subscriptions","parentId":"wrk_531746874d7b40d9a80c930c58d287b1","_type":"request_group"},{"_id":"req_03daed50d251472ca28e864b012be4ce","authentication":{"token":"{{ token  }}","type":"bearer"},"body":{},"created":1568130433938,"description":"","headers":[],"isPrivate":false,"metaSortKey":-1568130433938,"method":"POST","modified":1568137265043,"name":"Create","parameters":[],"parentId":"fld_6103a24d36194f93ac5815061b1c8830","settingDisableRenderRequestBody":false,"settingEncodeUrl":true,"settingRebuildPath":true,"settingSendCookies":true,"settingStoreCookies":true,"url":"{{ base_url  }}/meetups/2/subscriptions","_type":"request"},{"_id":"req_400552442ae14020ba4f8e3bce9bc3c0","authentication":{"token":"{{ token  }}","type":"bearer"},"body":{},"created":1568129892795,"description":"","headers":[],"isPrivate":false,"metaSortKey":-1568129892795,"method":"DELETE","modified":1568130176157,"name":"Delete","parameters":[],"parentId":"fld_41d6557a1e334764930268e1507815b4","settingDisableRenderRequestBody":false,"settingEncodeUrl":true,"settingRebuildPath":true,"settingSendCookies":true,"settingStoreCookies":true,"url":"{{ base_url  }}/meetups/7","_type":"request"},{"_id":"fld_41d6557a1e334764930268e1507815b4","created":1568043668794,"description":"","environment":{},"environmentPropertyOrder":null,"metaSortKey":-1568043668794,"modified":1568043668794,"name":"Meetups","parentId":"wrk_531746874d7b40d9a80c930c58d287b1","_type":"request_group"},{"_id":"req_de676e5b760a45038659026bde39a284","authentication":{"token":"{{ token  }}","type":"bearer"},"body":{"mimeType":"application/json","text":"{\n\t\"title\": \"Teste\",\n\t\"description\": \"Teste de udate\",\n\t\"location\": \"São Paulo/SP\",\n\t\"date\": \"2017-11-26T11:00:00-03:00\",\n\t\"file_id\": 1\n}"},"created":1568129274926,"description":"","headers":[{"id":"pair_1963766e870e4132bff4b8c599977ca9","name":"Content-Type","value":"application/json"}],"isPrivate":false,"metaSortKey":-1568129274926,"method":"PUT","modified":1568137186257,"name":"Update","parameters":[],"parentId":"fld_41d6557a1e334764930268e1507815b4","settingDisableRenderRequestBody":false,"settingEncodeUrl":true,"settingRebuildPath":true,"settingSendCookies":true,"settingStoreCookies":true,"url":"{{ base_url  }}/meetups/3","_type":"request"},{"_id":"req_1c605d90d32a43ba87aa9dd6036f8b78","authentication":{"token":"{{ token  }}","type":"bearer"},"body":{},"created":1568045755297,"description":"","headers":[],"isPrivate":false,"metaSortKey":-1568045755297,"method":"GET","modified":1568136569375,"name":"List","parameters":[{"disabled":true,"id":"pair_c6d2e2a66fc44c309978663a3b0e8503","name":"date","value":"2019-09-11"},{"id":"pair_f202c82e450d4fab883f7fa019dba98f","name":"","value":""}],"parentId":"fld_41d6557a1e334764930268e1507815b4","settingDisableRenderRequestBody":false,"settingEncodeUrl":true,"settingRebuildPath":true,"settingSendCookies":true,"settingStoreCookies":true,"url":"{{ base_url  }}/meetups","_type":"request"},{"_id":"req_acac1ec57fec4e2b807f81961a10b83a","authentication":{"token":"{{ token  }}","type":"bearer"},"body":{"mimeType":"application/json","text":"{\n\t\"title\": \"RS/RX - 2\",\n\t\"description\": \"RocketSeat Experience\",\n\t\"location\": \"São Paulo/SP\",\n\t\"date\": \"2019-09-11T18:00:00-03:00\",\n\t\"file_id\": 1\n}"},"created":1568043689346,"description":"","headers":[{"id":"pair_36a537c944cc4e46a07601777e3a67cb","name":"Content-Type","value":"application/json"}],"isPrivate":false,"metaSortKey":-1568043689346,"method":"POST","modified":1568136718426,"name":"Create","parameters":[],"parentId":"fld_41d6557a1e334764930268e1507815b4","settingDisableRenderRequestBody":false,"settingEncodeUrl":true,"settingRebuildPath":true,"settingSendCookies":true,"settingStoreCookies":true,"url":"{{ base_url  }}/meetups","_type":"request"},{"_id":"req_54546182a11a493592d814fd9b584d39","authentication":{"token":"{{ token  }}","type":"bearer"},"body":{"mimeType":"multipart/form-data","params":[{"fileName":"/home/adriano/Downloads/IMG-20180803-WA0018.jpg","id":"pair_432c75e6a45843df9f8262f07d7a61b5","name":"file","type":"file","value":""}]},"created":1568036623441,"description":"","headers":[{"id":"pair_2f422818ef8e440bacfd805dd94cbea7","name":"Content-Type","value":"multipart/form-data"}],"isPrivate":false,"metaSortKey":-1568036623441,"method":"POST","modified":1568135907229,"name":"Create","parameters":[],"parentId":"fld_e788dd56d37a4a9f9b50e56183e62db0","settingDisableRenderRequestBody":false,"settingEncodeUrl":true,"settingRebuildPath":true,"settingSendCookies":true,"settingStoreCookies":true,"url":"{{ base_url  }}/files","_type":"request"},{"_id":"fld_e788dd56d37a4a9f9b50e56183e62db0","created":1568036613623,"description":"","environment":{},"environmentPropertyOrder":null,"metaSortKey":-1568036613623,"modified":1568036613623,"name":"Files","parentId":"wrk_531746874d7b40d9a80c930c58d287b1","_type":"request_group"},{"_id":"req_90fbcf7f6ebe4f7495b08b9140e4b465","authentication":{},"body":{"mimeType":"application/json","text":"{\n\t\"name\": \"silva.souza.adriano\",\n\t\"email\": \"silva.souza.adriano@gmail.com\",\n\t\"password\": \"123456\"\n}"},"created":1566858526452,"description":"","headers":[{"id":"pair_2f16e7cd43a944179f37b11754c35fb6","name":"Content-Type","value":"application/json"}],"isPrivate":false,"metaSortKey":-1566858526452,"method":"POST","modified":1568135772478,"name":"Create","parameters":[],"parentId":"fld_2e1e23bc24e0453997cb8a4d74371762","settingDisableRenderRequestBody":false,"settingEncodeUrl":true,"settingRebuildPath":true,"settingSendCookies":true,"settingStoreCookies":true,"url":"{{ base_url  }}/users","_type":"request"},{"_id":"fld_2e1e23bc24e0453997cb8a4d74371762","created":1566858309091,"description":"","environment":{},"environmentPropertyOrder":null,"metaSortKey":-1566858309091,"modified":1566858309091,"name":"Users","parentId":"wrk_531746874d7b40d9a80c930c58d287b1","_type":"request_group"},{"_id":"req_728a53d66f724a39863ff2e25b37a28f","authentication":{"token":"{{ token  }}","type":"bearer"},"body":{"mimeType":"application/json","text":"{\n\t\"name\": \"Grace Kelly de Oliveira de Souza\",\n\t\"email\": \"gracekellyos@gmail.com\",\n\t\"oldPassword\": \"123456\",\n\t\"password\": \"123456\",\n\t\"confirmPassword\": \"123456\",\n\t\"file_id\": 1\n}"},"created":1566858827689,"description":"","headers":[{"id":"pair_2f16e7cd43a944179f37b11754c35fb6","name":"Content-Type","value":"application/json"}],"isPrivate":false,"metaSortKey":-1566731444321,"method":"PUT","modified":1568136417155,"name":"Update","parameters":[],"parentId":"fld_2e1e23bc24e0453997cb8a4d74371762","settingDisableRenderRequestBody":false,"settingEncodeUrl":true,"settingRebuildPath":true,"settingSendCookies":true,"settingStoreCookies":true,"url":"{{ base_url  }}/users","_type":"request"},{"_id":"req_4e9b6f0aba484b1cbc4a6904c725b5ee","authentication":{},"body":{"mimeType":"application/json","text":"{\n\t\"email\": \"silva.souza.adriano@gmail.com\",\n\t\"password\": \"123456\"\n}"},"created":1566858777612,"description":"","headers":[{"id":"pair_b29fe364de6044139c682c051352e68b","name":"Content-Type","value":"application/json"}],"isPrivate":false,"metaSortKey":-1566858777612,"method":"POST","modified":1568136449409,"name":"Create","parameters":[],"parentId":"fld_fbd8852082b247ae8fadc442f51b782b","settingDisableRenderRequestBody":false,"settingEncodeUrl":true,"settingRebuildPath":true,"settingSendCookies":true,"settingStoreCookies":true,"url":"{{ base_url  }}/sessions","_type":"request"},{"_id":"fld_fbd8852082b247ae8fadc442f51b782b","created":1566858301073,"description":"","environment":{},"environmentPropertyOrder":null,"metaSortKey":-1566858301073,"modified":1566858301073,"name":"Sessions","parentId":"wrk_531746874d7b40d9a80c930c58d287b1","_type":"request_group"},{"_id":"env_fa5dc6b758ab285ca699732c1a04f541abbcc5e4","color":null,"created":1566858214729,"data":{"base_url":"http://localhost:3333","token":"eyJhbGciOiJIUzI1NiIsInR5cCI6IkpXVCJ9.eyJpZCI6MiwiaWF0IjoxNTY4MTM2NDUzLCJleHAiOjE1Njg3NDEyNTN9.dk9MVfzjAsI7z9wpl_aTrPXrpBZeWcbkEUfwmtvDtsE"},"dataPropertyOrder":{"&":["base_url","token"]},"isPrivate":false,"metaSortKey":1566858214729,"modified":1568136643298,"name":"Base Environment","parentId":"wrk_531746874d7b40d9a80c930c58d287b1","_type":"environment"},{"_id":"jar_fa5dc6b758ab285ca699732c1a04f541abbcc5e4","cookies":[],"created":1566858214730,"modified":1566858214730,"name":"Default Jar","parentId":"wrk_531746874d7b40d9a80c930c58d287b1","_type":"cookie_jar"}]}